LICENSE
MANIFEST.in
README.rst
setup.py
betterdialogs/__init__.py
betterdialogs/betterdialog.py
betterdialogs/bettertext.py
betterdialogs/datedialog.py
betterdialogs/entrydialog.py
betterdialogs/images.py
betterdialogs/mainframe.py
betterdialogs.egg-info/PKG-INFO
betterdialogs.egg-info/SOURCES.txt
betterdialogs.egg-info/dependency_links.txt
betterdialogs.egg-info/requires.txt
betterdialogs.egg-info/top_level.txt