Metadata-Version: 1.1
Name: betterdialogs
Version: 1.0.0
Summary: Simple boilerplate library for tkinter GUIs (Python 3 ONLY)
Home-page: https://github.com/morngrar/betterdialogs
Author: Svein-Kåre Bjørnsen
Author-email: sveinkare@gmail.com
License: GPL
Platform: UNKNOWN
Classifier: Development Status :: 5 - Production/Stable
Classifier: Intended Audience :: Developers
Classifier: License :: OSI Approved :: GNU General Public License v3 (GPLv3)
Classifier: Programming Language :: Python :: 3 :: Only
Classifier: Topic :: Utilities
